Metadata-Version: 1.0
Name: wsrpc
Version: 0.0.2
Summary: UNKNOWN
Home-page: UNKNOWN
Author: Brett Graham
Author-email: braingram720@gmail.com
License: UNKNOWN
Platform: UNKNOWN
